sphn-0.2.0.dist-info/METADATA
sphn-0.2.0.dist-info/WHEEL
sphn-0.2.0.dist-info/licenses/LICENSE
sphn/__init__.py
sphn/__init__.pyi
sphn/sphn.cp313-win_amd64.pyd
sphn-0.2.0.dist-info/RECORD
