Metadata-Version: 2.4
Name: sphn
Version: 0.2.0
Classifier: Programming Language :: Rust
Classifier: Programming Language :: Python :: Implementation :: CPython
Classifier: Programming Language :: Python :: Implementation :: PyPy
License-File: LICENSE
Summary: pyo3 wrappers to read/write audio files
Keywords: pyo3,audio
License: MIT/Apache-2.0
Requires-Python: >=3.8
Project-URL: Source Code, https://github.com/LaurentMazare/sphn
